<?xml version="1.0" encoding="utf-8"?>
<!DOCTYPE hibernate-mapping PUBLIC "-//Hibernate/Hibernate Mapping DTD 3.0//EN"
"http://hibernate.sourceforge.net/hibernate-mapping-3.0.dtd">
<!-- 
    Mapping file autogenerated by MyEclipse Persistence Tools
-->
<hibernate-mapping>
    <class name="com.alibaba.dubbo.demo.bean.SysShopinfo" table="sys_shopinfo" catalog="posdb">
        <id name="shopid" type="java.lang.Integer">
            <column name="shopid" />
            <generator class="identity" />
        </id>
        <property name="shopcode" type="java.lang.String">
            <column name="shopcode" length="30" />
        </property>
        <property name="shopname" type="java.lang.String">
            <column name="shopname" length="60" />
        </property>
        <property name="shopaddr" type="java.lang.String">
            <column name="shopaddr" length="100" />
        </property>
        <property name="longitude" type="java.lang.Double">
            <column name="longitude" precision="22" scale="0" />
        </property>
        <property name="latitude" type="java.lang.Double">
            <column name="latitude" precision="22" scale="0" />
        </property>
        <property name="shopleader" type="java.lang.String">
            <column name="shopleader" length="60" />
        </property>
        <property name="leaderphone" type="java.lang.String">
            <column name="leaderphone" length="60" />
        </property>
        <property name="manager" type="java.lang.String">
            <column name="manager" length="60" />
        </property>
        <property name="managerphone" type="java.lang.String">
            <column name="managerphone" length="20" />
        </property>
        <property name="manageremail" type="java.lang.String">
            <column name="manageremail" length="60" />
        </property>
        <property name="managerweixin" type="java.lang.String">
            <column name="managerweixin" length="60" />
        </property>
        <property name="remark" type="java.lang.String">
            <column name="remark" length="100" />
        </property>
    </class>
</hibernate-mapping>
